sspo_db/__init__.py
sspo_db/application/__init__.py
sspo_db/application/abstract_application.py
sspo_db/application/factories.py
sspo_db/application/activity/__init__.py
sspo_db/application/activity/application.py
sspo_db/application/artifact/__init__.py
sspo_db/application/artifact/application.py
sspo_db/application/core/__init__.py
sspo_db/application/core/application.py
sspo_db/application/organization/__init__.py
sspo_db/application/organization/application.py
sspo_db/application/process/__init__.py
sspo_db/application/process/application.py
sspo_db/application/stakeholder/__init__.py
sspo_db/application/stakeholder/application.py
sspo_db/application/stakeholder_participation/__init__.py
sspo_db/application/stakeholder_participation/application.py
sspo_db/config/__init__.py
sspo_db/config/base.py
sspo_db/config/config.py
sspo_db/model/__init__.py
sspo_db/model/factories.py
sspo_db/model/activity/__init__.py
sspo_db/model/activity/models.py
sspo_db/model/artifact/__init__.py
sspo_db/model/artifact/models.py
sspo_db/model/core/__init__.py
sspo_db/model/core/models.py
sspo_db/model/organization/__init__.py
sspo_db/model/organization/models.py
sspo_db/model/process/__init__.py
sspo_db/model/process/models.py
sspo_db/model/relationship/__init__.py
sspo_db/model/relationship/model.py
sspo_db/model/stakeholder/__init__.py
sspo_db/model/stakeholder/models.py
sspo_db/model/stakeholder_participation/__init__.py
sspo_db/model/stakeholder_participation/models.py
sspo_db/service/__init__.py
sspo_db/service/base_service.py
sspo_db/service/factories.py
sspo_db/service/activity/__init__.py
sspo_db/service/activity/service.py
sspo_db/service/artifact/__init__.py
sspo_db/service/artifact/service.py
sspo_db/service/core/__init__.py
sspo_db/service/core/service.py
sspo_db/service/organization/__init__.py
sspo_db/service/organization/service.py
sspo_db/service/process/__init__.py
sspo_db/service/process/service.py
sspo_db/service/stakeholder/__init__.py
sspo_db-10.0.2.dist-info/METADATA
sspo_db-10.0.2.dist-info/WHEEL
sspo_db-10.0.2.dist-info/top_level.txt
sspo_db-10.0.2.dist-info/RECORD
